InfTDA/__init__.py
InfTDA/differential_privacy.py
InfTDA/mechanism.py
InfTDA/optimization.py
inf_tda-0.1.dist-info/LICENSE
inf_tda-0.1.dist-info/METADATA
inf_tda-0.1.dist-info/WHEEL
inf_tda-0.1.dist-info/top_level.txt
inf_tda-0.1.dist-info/RECORD
