Metadata-Version: 2.2
Name: inf_tda
Version: 0.1
Summary: Differentially private hierarchical queries with a Top-Down Approach for pandas Series with MultiIndex
Home-page: https://github.com/NynsenFaber/InfTDA_py
Author: Fabrizio Boninsegna
Classifier: Development Status :: 4 - Beta
Classifier: Programming Language :: Python :: 3
Classifier: License :: OSI Approved :: MIT License
Classifier: Operating System :: OS Independent
Requires-Python: >=3.6
License-File: LICENSE
Requires-Dist: pandas>=2.2.2
Requires-Dist: opendp>=0.12
Dynamic: author
Dynamic: classifier
Dynamic: description
Dynamic: description-content-type
Dynamic: home-page
Dynamic: requires-dist
Dynamic: requires-python
Dynamic: summary
